{
  "type": "cypher",
  "source": "Cypher System Reference Document 2025-08-22",
  "title": "Washing Round",
  "slug": "washing_round",
  "category": "Dark Magic And Occult Cyphers",
  "level": "1d6",
  "form": "“BATH” scribed on bullet case; leaves a sudsy, fresh-smelling streak in the air when fired",
  "effect": "When this round is fired from a gun, additional attacks made from the gun gain the same benefit for the next minute. Instead of taking damage, a successfully attacked target is immediately subject to a good scrubbing, leaving them and their clothes a bit damp, but clean and as odor-free as if they’d washed and laundered in the finest bathhouse. If the cypher is level 5 or higher, the effect is so potent that the target’s positive interaction tasks are eased for an hour afterward.",
  "depletion": null,
  "settings": [
    "csrd_core",
    "fantasy",
    "horror"
  ],
  "setting": "csrd_core"
}